matchms_plotly/__init__.py
matchms_plotly/plot.py
matchms_plotly/py.typed
matchms_plotly-0.1.4.dist-info/LICENSE
matchms_plotly-0.1.4.dist-info/WHEEL
matchms_plotly-0.1.4.dist-info/METADATA
matchms_plotly-0.1.4.dist-info/RECORD
